{
    "@schema": "https://raw.githubusercontent.com/slicer/slicer/master/Modules/Loadable/Markups/Resources/Schema/markups-schema-v1.0.3.json#",
    "markups": [
        {
            "type": "Fiducial",
            "coordinateSystem": "LPS",
            "coordinateUnits": "mm",
            "locked": false,
            "fixedNumberOfControlPoints": false,
            "labelFormat": "%N-%d",
            "lastUsedControlPointNumber": 59,
            "controlPoints": [
                {
                    "id": "1",
                    "label": "F_2-1",
                    "description": "",
                    "associatedNodeID": "vtkMRMLScalarVolumeNode3",
                    "position": [-48.09754955832939, -131.88768088805637, -147.37799072265626],
                    "orientation": [-1.0, -0.0, -0.0, -0.0, -1.0, -0.0, 0.0, 0.0, 1.0],
                    "selected": true,
                    "locked": false,
                    "visibility": true,
                    "positionStatus": "defined"
                },
                {
                    "id": "2",
                    "label": "F_2-2",
                    "description": "",
                    "associatedNodeID": "vtkMRMLScalarVolumeNode3",
                    "position": [-47.83876516911091, -128.8685296805074, -147.37799072265626],
                    "orientation": [-1.0, -0.0, -0.0, -0.0, -1.0, -0.0, 0.0, 0.0, 1.0],
                    "selected": true,
                    "locked": false,
                    "visibility": true,
                    "positionStatus": "defined"
                },
                {
                    "id": "3",
                    "label": "F_2-3",
                    "description": "",
                    "associatedNodeID": "vtkMRMLScalarVolumeNode3",
                    "position": [-47.23493492760111, -125.33180969452147, -147.37799072265626],
                    "orientation": [-1.0, -0.0, -0.0, -0.0, -1.0, -0.0, 0.0, 0.0, 1.0],
                    "selected": true,
                    "locked": false,
                    "visibility": true,
                    "positionStatus": "defined"
                },
                {
                    "id": "4",
                    "label": "F_2-4",
                    "description": "",
                    "associatedNodeID": "vtkMRMLScalarVolumeNode3",
                    "position": [-46.19979737072718, -122.22639702389968, -147.37799072265626],
                    "orientation": [-1.0, -0.0, -0.0, -0.0, -1.0, -0.0, 0.0, 0.0, 1.0],
                    "selected": true,
                    "locked": false,
                    "visibility": true,
                    "positionStatus": "defined"
                },
                {
                    "id": "5",
                    "label": "F_2-5",
                    "description": "",
                    "associatedNodeID": "vtkMRMLScalarVolumeNode3",
                    "position": [-44.819613961561937, -119.29350727942354, -147.37799072265626],
                    "orientation": [-1.0, -0.0, -0.0, -0.0, -1.0, -0.0, 0.0, 0.0, 1.0],
                    "selected": true,
                    "locked": false,
                    "visibility": true,
                    "positionStatus": "defined"
                },
                {
                    "id": "6",
                    "label": "F_2-6",
                    "description": "",
                    "associatedNodeID": "vtkMRMLScalarVolumeNode3",
                    "position": [-43.525692015469527, -116.87818631338436, -147.37799072265626],
                    "orientation": [-1.0, -0.0, -0.0, -0.0, -1.0, -0.0, 0.0, 0.0, 1.0],
                    "selected": true,
                    "locked": false,
                    "visibility": true,
                    "positionStatus": "defined"
                },
                {
                    "id": "7",
                    "label": "F_2-7",
                    "description": "",
                    "associatedNodeID": "vtkMRMLScalarVolumeNode3",
                    "position": [-42.318031532449939, -115.23921851500065, -147.37799072265626],
                    "orientation": [-1.0, -0.0, -0.0, -0.0, -1.0, -0.0, 0.0, 0.0, 1.0],
                    "selected": true,
                    "locked": false,
                    "visibility": true,
                    "positionStatus": "defined"
                },
                {
                    "id": "8",
                    "label": "F_2-8",
                    "description": "",
                    "associatedNodeID": "vtkMRMLScalarVolumeNode3",
                    "position": [-42.318031532449939, -115.92931021958326, -150.37799072265626],
                    "orientation": [-1.0, -0.0, -0.0, -0.0, -1.0, -0.0, 0.0, 0.0, 1.0],
                    "selected": true,
                    "locked": false,
                    "visibility": true,
                    "positionStatus": "defined"
                },
                {
                    "id": "9",
                    "label": "F_2-9",
                    "description": "",
                    "associatedNodeID": "vtkMRMLScalarVolumeNode3",
                    "position": [-44.73335249848911, -117.99958533333113, -150.37799072265626],
                    "orientation": [-1.0, -0.0, -0.0, -0.0, -1.0, -0.0, 0.0, 0.0, 1.0],
                    "selected": true,
                    "locked": false,
                    "visibility": true,
                    "positionStatus": "defined"
                },
                {
                    "id": "10",
                    "label": "F_2-10",
                    "description": "",
                    "associatedNodeID": "vtkMRMLScalarVolumeNode3",
                    "position": [-46.286058833800009, -120.75995215166161, -150.37799072265626],
                    "orientation": [-1.0, -0.0, -0.0, -0.0, -1.0, -0.0, 0.0, 0.0, 1.0],
                    "selected": true,
                    "locked": false,
                    "visibility": true,
                    "positionStatus": "defined"
                },
                {
                    "id": "11",
                    "label": "F_2-11",
                    "description": "",
                    "associatedNodeID": "vtkMRMLScalarVolumeNode3",
                    "position": [-47.14867346452829, -122.9164887284823, -150.37799072265626],
                    "orientation": [-1.0, -0.0, -0.0, -0.0, -1.0, -0.0, 0.0, 0.0, 1.0],
                    "selected": true,
                    "locked": false,
                    "visibility": true,
                    "positionStatus": "defined"
                },
                {
                    "id": "12",
                    "label": "F_2-12",
                    "description": "",
                    "associatedNodeID": "vtkMRMLScalarVolumeNode3",
                    "position": [-48.01128809525656, -125.50433262066713, -150.37799072265626],
                    "orientation": [-1.0, -0.0, -0.0, -0.0, -1.0, -0.0, 0.0, 0.0, 1.0],
                    "selected": true,
                    "locked": false,
                    "visibility": true,
                    "positionStatus": "defined"
                },
                {
                    "id": "13",
                    "label": "F_2-13",
                    "description": "",
                    "associatedNodeID": "vtkMRMLScalarVolumeNode3",
                    "position": [-48.356333947547877, -127.574607734415, -150.37799072265626],
                    "orientation": [-1.0, -0.0, -0.0, -0.0, -1.0, -0.0, 0.0, 0.0, 1.0],
                    "selected": true,
                    "locked": false,
                    "visibility": true,
                    "positionStatus": "defined"
                },
                {
                    "id": "14",
                    "label": "F_2-14",
                    "description": "",
                    "associatedNodeID": "vtkMRMLScalarVolumeNode3",
                    "position": [-48.52885687369353, -129.4723599220172, -150.37799072265626],
                    "orientation": [-1.0, -0.0, -0.0, -0.0, -1.0, -0.0, 0.0, 0.0, 1.0],
                    "selected": true,
                    "locked": false,
                    "visibility": true,
                    "positionStatus": "defined"
                },
                {
                    "id": "15",
                    "label": "F_2-15",
                    "description": "",
                    "associatedNodeID": "vtkMRMLScalarVolumeNode3",
                    "position": [-48.356333947547877, -132.06020381420204, -150.37799072265626],
                    "orientation": [-1.0, -0.0, -0.0, -0.0, -1.0, -0.0, 0.0, 0.0, 1.0],
                    "selected": true,
                    "locked": false,
                    "visibility": true,
                    "positionStatus": "defined"
                },
                {
                    "id": "16",
                    "label": "F_2-16",
                    "description": "",
                    "associatedNodeID": "vtkMRMLScalarVolumeNode3",
                    "position": [-41.541678364794488, -114.8079111996365, -150.37799072265626],
                    "orientation": [-1.0, -0.0, -0.0, -0.0, -1.0, -0.0, 0.0, 0.0, 1.0],
                    "selected": true,
                    "locked": false,
                    "visibility": true,
                    "positionStatus": "defined"
                },
                {
                    "id": "17",
                    "label": "F_2-17",
                    "description": "",
                    "associatedNodeID": "vtkMRMLScalarVolumeNode3",
                    "position": [-41.627939827867319, -115.41174144114629, -153.37799072265626],
                    "orientation": [-1.0, -0.0, -0.0, -0.0, -1.0, -0.0, 0.0, 0.0, 1.0],
                    "selected": true,
                    "locked": false,
                    "visibility": true,
                    "positionStatus": "defined"
                },
                {
                    "id": "18",
                    "label": "F_2-18",
                    "description": "",
                    "associatedNodeID": "vtkMRMLScalarVolumeNode3",
                    "position": [-43.525692015469527, -116.96444777645719, -153.37799072265626],
                    "orientation": [-1.0, -0.0, -0.0, -0.0, -1.0, -0.0, 0.0, 0.0, 1.0],
                    "selected": true,
                    "locked": false,
                    "visibility": true,
                    "positionStatus": "defined"
                },
                {
                    "id": "19",
                    "label": "F_2-19",
                    "description": "",
                    "associatedNodeID": "vtkMRMLScalarVolumeNode3",
                    "position": [-45.50970566614456, -119.8110760578605, -153.37799072265626],
                    "orientation": [-1.0, -0.0, -0.0, -0.0, -1.0, -0.0, 0.0, 0.0, 1.0],
                    "selected": true,
                    "locked": false,
                    "visibility": true,
                    "positionStatus": "defined"
                },
                {
                    "id": "20",
                    "label": "F_2-20",
                    "description": "",
                    "associatedNodeID": "vtkMRMLScalarVolumeNode3",
                    "position": [-46.11353590765435, -121.62256678238988, -153.37799072265626],
                    "orientation": [-1.0, -0.0, -0.0, -0.0, -1.0, -0.0, 0.0, 0.0, 1.0],
                    "selected": true,
                    "locked": false,
                    "visibility": true,
                    "positionStatus": "defined"
                },
                {
                    "id": "21",
                    "label": "F_2-21",
                    "description": "",
                    "associatedNodeID": "vtkMRMLScalarVolumeNode3",
                    "position": [-46.54484322301849, -123.17527311770079, -153.37799072265626],
                    "orientation": [-1.0, -0.0, -0.0, -0.0, -1.0, -0.0, 0.0, 0.0, 1.0],
                    "selected": true,
                    "locked": false,
                    "visibility": true,
                    "positionStatus": "defined"
                },
                {
                    "id": "22",
                    "label": "F_2-22",
                    "description": "",
                    "associatedNodeID": "vtkMRMLScalarVolumeNode3",
                    "position": [-47.23493492760111, -125.59059408373996, -153.37799072265626],
                    "orientation": [-1.0, -0.0, -0.0, -0.0, -1.0, -0.0, 0.0, 0.0, 1.0],
                    "selected": true,
                    "locked": false,
                    "visibility": true,
                    "positionStatus": "defined"
                },
                {
                    "id": "23",
                    "label": "F_2-23",
                    "description": "",
                    "associatedNodeID": "vtkMRMLScalarVolumeNode3",
                    "position": [-47.49371931681959, -127.574607734415, -153.37799072265626],
                    "orientation": [-1.0, -0.0, -0.0, -0.0, -1.0, -0.0, 0.0, 0.0, 1.0],
                    "selected": true,
                    "locked": false,
                    "visibility": true,
                    "positionStatus": "defined"
                },
                {
                    "id": "24",
                    "label": "F_2-24",
                    "description": "",
                    "associatedNodeID": "vtkMRMLScalarVolumeNode3",
                    "position": [-47.57998077989242, -129.8174057743085, -153.37799072265626],
                    "orientation": [-1.0, -0.0, -0.0, -0.0, -1.0, -0.0, 0.0, 0.0, 1.0],
                    "selected": true,
                    "locked": false,
                    "visibility": true,
                    "positionStatus": "defined"
                },
                {
                    "id": "25",
                    "label": "F_2-25",
                    "description": "",
                    "associatedNodeID": "vtkMRMLScalarVolumeNode3",
                    "position": [-47.66624224296525, -130.93880479425529, -153.37799072265626],
                    "orientation": [-1.0, -0.0, -0.0, -0.0, -1.0, -0.0, 0.0, 0.0, 1.0],
                    "selected": true,
                    "locked": false,
                    "visibility": true,
                    "positionStatus": "defined"
                },
                {
                    "id": "26",
                    "label": "F_2-26",
                    "description": "",
                    "associatedNodeID": "vtkMRMLScalarVolumeNode3",
                    "position": [-42.318031532449939, -116.01557168265609, -138.37799072265626],
                    "orientation": [-1.0, -0.0, -0.0, -0.0, -1.0, -0.0, 0.0, 0.0, 1.0],
                    "selected": true,
                    "locked": false,
                    "visibility": true,
                    "positionStatus": "defined"
                },
                {
                    "id": "27",
                    "label": "F_2-27",
                    "description": "",
                    "associatedNodeID": "vtkMRMLScalarVolumeNode3",
                    "position": [-44.215783720052147, -117.22323216567568, -138.37799072265626],
                    "orientation": [-1.0, -0.0, -0.0, -0.0, -1.0, -0.0, 0.0, 0.0, 1.0],
                    "selected": true,
                    "locked": false,
                    "visibility": true,
                    "positionStatus": "defined"
                },
                {
                    "id": "28",
                    "label": "F_2-28",
                    "description": "",
                    "associatedNodeID": "vtkMRMLScalarVolumeNode3",
                    "position": [-45.50970566614456, -119.2072458163507, -138.37799072265626],
                    "orientation": [-1.0, -0.0, -0.0, -0.0, -1.0, -0.0, 0.0, 0.0, 1.0],
                    "selected": true,
                    "locked": false,
                    "visibility": true,
                    "positionStatus": "defined"
                },
                {
                    "id": "29",
                    "label": "F_2-29",
                    "description": "",
                    "associatedNodeID": "vtkMRMLScalarVolumeNode3",
                    "position": [-46.372320296872839, -121.0187365408801, -138.37799072265626],
                    "orientation": [-1.0, -0.0, -0.0, -0.0, -1.0, -0.0, 0.0, 0.0, 1.0],
                    "selected": true,
                    "locked": false,
                    "visibility": true,
                    "positionStatus": "defined"
                },
                {
                    "id": "30",
                    "label": "F_2-30",
                    "description": "",
                    "associatedNodeID": "vtkMRMLScalarVolumeNode3",
                    "position": [-46.976150538382629, -123.00275019155512, -138.37799072265626],
                    "orientation": [-1.0, -0.0, -0.0, -0.0, -1.0, -0.0, 0.0, 0.0, 1.0],
                    "selected": true,
                    "locked": false,
                    "visibility": true,
                    "positionStatus": "defined"
                },
                {
                    "id": "31",
                    "label": "F_2-31",
                    "description": "",
                    "associatedNodeID": "vtkMRMLScalarVolumeNode3",
                    "position": [-47.49371931681959, -124.98676384223016, -138.37799072265626],
                    "orientation": [-1.0, -0.0, -0.0, -0.0, -1.0, -0.0, 0.0, 0.0, 1.0],
                    "selected": true,
                    "locked": false,
                    "visibility": true,
                    "positionStatus": "defined"
                },
                {
                    "id": "32",
                    "label": "F_2-32",
                    "description": "",
                    "associatedNodeID": "vtkMRMLScalarVolumeNode3",
                    "position": [-47.75250370603808, -127.14330041905086, -138.37799072265626],
                    "orientation": [-1.0, -0.0, -0.0, -0.0, -1.0, -0.0, 0.0, 0.0, 1.0],
                    "selected": true,
                    "locked": false,
                    "visibility": true,
                    "positionStatus": "defined"
                },
                {
                    "id": "33",
                    "label": "F_2-33",
                    "description": "",
                    "associatedNodeID": "vtkMRMLScalarVolumeNode3",
                    "position": [-47.83876516911091, -129.4723599220172, -138.37799072265626],
                    "orientation": [-1.0, -0.0, -0.0, -0.0, -1.0, -0.0, 0.0, 0.0, 1.0],
                    "selected": true,
                    "locked": false,
                    "visibility": true,
                    "positionStatus": "defined"
                },
                {
                    "id": "34",
                    "label": "F_2-34",
                    "description": "",
                    "associatedNodeID": "vtkMRMLScalarVolumeNode3",
                    "position": [-44.92759202062803, -125.9388904045752, -156.81369988611935],
                    "orientation": [-1.0, -0.0, -0.0, -0.0, -1.0, -0.0, 0.0, 0.0, 1.0],
                    "selected": true,
                    "locked": false,
                    "visibility": true,
                    "positionStatus": "defined"
                },
                {
                    "id": "35",
                    "label": "F_2-35",
                    "description": "",
                    "associatedNodeID": "vtkMRMLScalarVolumeNode3",
                    "position": [-50.01086559436414, -125.9388904045752, -149.40664410724674],
                    "orientation": [-1.0, -0.0, -0.0, -0.0, -1.0, -0.0, 0.0, 0.0, 1.0],
                    "selected": true,
                    "locked": false,
                    "visibility": true,
                    "positionStatus": "defined"
                },
                {
                    "id": "36",
                    "label": "F_2-36",
                    "description": "",
                    "associatedNodeID": "vtkMRMLScalarVolumeNode3",
                    "position": [-50.3013383700062, -125.9388904045752, -144.90431608479475],
                    "orientation": [-1.0, -0.0, -0.0, -0.0, -1.0, -0.0, 0.0, 0.0, 1.0],
                    "selected": true,
                    "locked": false,
                    "visibility": true,
                    "positionStatus": "defined"
                },
                {
                    "id": "37",
                    "label": "F_2-37",
                    "description": "",
                    "associatedNodeID": "vtkMRMLScalarVolumeNode3",
                    "position": [-50.3013383700062, -125.9388904045752, -141.70911555273205],
                    "orientation": [-1.0, -0.0, -0.0, -0.0, -1.0, -0.0, 0.0, 0.0, 1.0],
                    "selected": true,
                    "locked": false,
                    "visibility": true,
                    "positionStatus": "defined"
                },
                {
                    "id": "38",
                    "label": "F_2-38",
                    "description": "",
                    "associatedNodeID": "vtkMRMLScalarVolumeNode3",
                    "position": [-49.865629206543108, -125.9388904045752, -139.24009695977453],
                    "orientation": [-1.0, -0.0, -0.0, -0.0, -1.0, -0.0, 0.0, 0.0, 1.0],
                    "selected": true,
                    "locked": false,
                    "visibility": true,
                    "positionStatus": "defined"
                },
                {
                    "id": "39",
                    "label": "F_2-39",
                    "description": "",
                    "associatedNodeID": "vtkMRMLScalarVolumeNode3",
                    "position": [-49.42992004308001, -125.9388904045752, -137.64249669374318],
                    "orientation": [-1.0, -0.0, -0.0, -0.0, -1.0, -0.0, 0.0, 0.0, 1.0],
                    "selected": true,
                    "locked": false,
                    "visibility": true,
                    "positionStatus": "defined"
                },
                {
                    "id": "40",
                    "label": "F_2-40",
                    "description": "",
                    "associatedNodeID": "vtkMRMLScalarVolumeNode3",
                    "position": [-48.41326532833279, -125.9388904045752, -134.73776893732254],
                    "orientation": [-1.0, -0.0, -0.0, -0.0, -1.0, -0.0, 0.0, 0.0, 1.0],
                    "selected": true,
                    "locked": false,
                    "visibility": true,
                    "positionStatus": "defined"
                },
                {
                    "id": "41",
                    "label": "F_2-41",
                    "description": "",
                    "associatedNodeID": "vtkMRMLScalarVolumeNode3",
                    "position": [-41.441918712923278, -122.2279529045752, -156.95893627394038],
                    "orientation": [-1.0, -0.0, -0.0, -0.0, -1.0, -0.0, 0.0, 0.0, 1.0],
                    "selected": true,
                    "locked": false,
                    "visibility": true,
                    "positionStatus": "defined"
                },
                {
                    "id": "42",
                    "label": "F_2-42",
                    "description": "",
                    "associatedNodeID": "vtkMRMLScalarVolumeNode3",
                    "position": [-43.76570091805978, -122.2279529045752, -154.7803904566249],
                    "orientation": [-1.0, -0.0, -0.0, -0.0, -1.0, -0.0, 0.0, 0.0, 1.0],
                    "selected": true,
                    "locked": false,
                    "visibility": true,
                    "positionStatus": "defined"
                },
                {
                    "id": "43",
                    "label": "F_2-43",
                    "description": "",
                    "associatedNodeID": "vtkMRMLScalarVolumeNode3",
                    "position": [-45.79901034755422, -122.2279529045752, -151.87566270020427],
                    "orientation": [-1.0, -0.0, -0.0, -0.0, -1.0, -0.0, 0.0, 0.0, 1.0],
                    "selected": true,
                    "locked": false,
                    "visibility": true,
                    "positionStatus": "defined"
                },
                {
                    "id": "44",
                    "label": "F_2-44",
                    "description": "",
                    "associatedNodeID": "vtkMRMLScalarVolumeNode3",
                    "position": [-47.5418470014066, -122.2279529045752, -143.59718859440549],
                    "orientation": [-1.0, -0.0, -0.0, -0.0, -1.0, -0.0, 0.0, 0.0, 1.0],
                    "selected": true,
                    "locked": false,
                    "visibility": true,
                    "positionStatus": "defined"
                },
                {
                    "id": "45",
                    "label": "F_2-45",
                    "description": "",
                    "associatedNodeID": "vtkMRMLScalarVolumeNode3",
                    "position": [-47.5418470014066, -122.2279529045752, -140.40198806234279],
                    "orientation": [-1.0, -0.0, -0.0, -0.0, -1.0, -0.0, 0.0, 0.0, 1.0],
                    "selected": true,
                    "locked": false,
                    "visibility": true,
                    "positionStatus": "defined"
                },
                {
                    "id": "46",
                    "label": "F_2-46",
                    "description": "",
                    "associatedNodeID": "vtkMRMLScalarVolumeNode3",
                    "position": [-47.68708338922763, -122.2279529045752, -137.49726030592215],
                    "orientation": [-1.0, -0.0, -0.0, -0.0, -1.0, -0.0, 0.0, 0.0, 1.0],
                    "selected": true,
                    "locked": false,
                    "visibility": true,
                    "positionStatus": "defined"
                },
                {
                    "id": "47",
                    "label": "F_2-47",
                    "description": "",
                    "associatedNodeID": "vtkMRMLScalarVolumeNode3",
                    "position": [-46.67042867448041, -122.2279529045752, -134.44729616168048],
                    "orientation": [-1.0, -0.0, -0.0, -0.0, -1.0, -0.0, 0.0, 0.0, 1.0],
                    "selected": true,
                    "locked": false,
                    "visibility": true,
                    "positionStatus": "defined"
                },
                {
                    "id": "48",
                    "label": "F_2-48",
                    "description": "",
                    "associatedNodeID": "vtkMRMLScalarVolumeNode3",
                    "position": [-46.23471951101732, -122.2279529045752, -133.14016867129119],
                    "orientation": [-1.0, -0.0, -0.0, -0.0, -1.0, -0.0, 0.0, 0.0, 1.0],
                    "selected": true,
                    "locked": false,
                    "visibility": true,
                    "positionStatus": "defined"
                },
                {
                    "id": "49",
                    "label": "F_2-49",
                    "description": "",
                    "associatedNodeID": "vtkMRMLScalarVolumeNode3",
                    "position": [-48.55850171615382, -129.6498279045752, -147.3733346777523],
                    "orientation": [-1.0, -0.0, -0.0, -0.0, -1.0, -0.0, 0.0, 0.0, 1.0],
                    "selected": true,
                    "locked": false,
                    "visibility": true,
                    "positionStatus": "defined"
                },
                {
                    "id": "50",
                    "label": "F_2-50",
                    "description": "",
                    "associatedNodeID": "vtkMRMLScalarVolumeNode3",
                    "position": [-49.42992004308001, -129.6498279045752, -144.1781341456896],
                    "orientation": [-1.0, -0.0, -0.0, -0.0, -1.0, -0.0, 0.0, 0.0, 1.0],
                    "selected": true,
                    "locked": false,
                    "visibility": true,
                    "positionStatus": "defined"
                },
                {
                    "id": "51",
                    "label": "F_2-51",
                    "description": "",
                    "associatedNodeID": "vtkMRMLScalarVolumeNode3",
                    "position": [-49.13944726743795, -129.6498279045752, -141.99958832837414],
                    "orientation": [-1.0, -0.0, -0.0, -0.0, -1.0, -0.0, 0.0, 0.0, 1.0],
                    "selected": true,
                    "locked": false,
                    "visibility": true,
                    "positionStatus": "defined"
                },
                {
                    "id": "52",
                    "label": "F_2-52",
                    "description": "",
                    "associatedNodeID": "vtkMRMLScalarVolumeNode3",
                    "position": [-44.49188285716494, -119.2592029045752, -153.90897212969873],
                    "orientation": [-1.0, -0.0, -0.0, -0.0, -1.0, -0.0, 0.0, 0.0, 1.0],
                    "selected": true,
                    "locked": false,
                    "visibility": true,
                    "positionStatus": "defined"
                },
                {
                    "id": "53",
                    "label": "F_2-53",
                    "description": "",
                    "associatedNodeID": "vtkMRMLScalarVolumeNode3",
                    "position": [-41.87762787638637, -119.2592029045752, -156.0875179470142],
                    "orientation": [-1.0, -0.0, -0.0, -0.0, -1.0, -0.0, 0.0, 0.0, 1.0],
                    "selected": true,
                    "locked": false,
                    "visibility": true,
                    "positionStatus": "defined"
                },
                {
                    "id": "54",
                    "label": "F_2-54",
                    "description": "",
                    "associatedNodeID": "vtkMRMLScalarVolumeNode3",
                    "position": [-46.08948312319628, -119.2592029045752, -135.17347810078565],
                    "orientation": [-1.0, -0.0, -0.0, -0.0, -1.0, -0.0, 0.0, 0.0, 1.0],
                    "selected": true,
                    "locked": false,
                    "visibility": true,
                    "positionStatus": "defined"
                },
                {
                    "id": "55",
                    "label": "F_2-55",
                    "description": "",
                    "associatedNodeID": "vtkMRMLScalarVolumeNode3",
                    "position": [-45.50853757191216, -117.78842163085938, -145.63049802389993],
                    "orientation": [-1.0, -0.0, -0.0, -0.0, -1.0, -0.0, 0.0, 0.0, 1.0],
                    "selected": true,
                    "locked": false,
                    "visibility": true,
                    "positionStatus": "defined"
                },
                {
                    "id": "56",
                    "label": "F_2-56",
                    "description": "",
                    "associatedNodeID": "vtkMRMLScalarVolumeNode3",
                    "position": [-45.653773959733189, -117.78842163085938, -140.83769722580588],
                    "orientation": [-1.0, -0.0, -0.0, -0.0, -1.0, -0.0, 0.0, 0.0, 1.0],
                    "selected": true,
                    "locked": false,
                    "visibility": true,
                    "positionStatus": "defined"
                },
                {
                    "id": "57",
                    "label": "F_2-57",
                    "description": "",
                    "associatedNodeID": "vtkMRMLScalarVolumeNode3",
                    "position": [-45.21806479627009, -117.78842163085938, -137.20678753028009],
                    "orientation": [-1.0, -0.0, -0.0, -0.0, -1.0, -0.0, 0.0, 0.0, 1.0],
                    "selected": true,
                    "locked": false,
                    "visibility": true,
                    "positionStatus": "defined"
                },
                {
                    "id": "58",
                    "label": "F_2-58",
                    "description": "",
                    "associatedNodeID": "vtkMRMLScalarVolumeNode3",
                    "position": [-44.49188285716494, -117.78842163085938, -134.59253254950154],
                    "orientation": [-1.0, -0.0, -0.0, -0.0, -1.0, -0.0, 0.0, 0.0, 1.0],
                    "selected": true,
                    "locked": false,
                    "visibility": true,
                    "positionStatus": "defined"
                },
                {
                    "id": "59",
                    "label": "F_2-59",
                    "description": "",
                    "associatedNodeID": "vtkMRMLScalarVolumeNode3",
                    "position": [-41.732391488565337, -117.78842163085938, -156.6684634982983],
                    "orientation": [-1.0, -0.0, -0.0, -0.0, -1.0, -0.0, 0.0, 0.0, 1.0],
                    "selected": true,
                    "locked": false,
                    "visibility": true,
                    "positionStatus": "defined"
                }
            ],
            "measurements": [],
            "display": {
                "visibility": false,
                "opacity": 1.0,
                "color": [0.4, 1.0, 0.0],
                "selectedColor": [1.0, 0.5000076295109484, 0.5000076295109484],
                "activeColor": [0.4, 1.0, 0.0],
                "propertiesLabelVisibility": false,
                "pointLabelsVisibility": true,
                "textScale": 3.0,
                "glyphType": "Sphere3D",
                "glyphScale": 3.0,
                "glyphSize": 5.0,
                "useGlyphScale": true,
                "sliceProjection": false,
                "sliceProjectionUseFiducialColor": true,
                "sliceProjectionOutlinedBehindSlicePlane": false,
                "sliceProjectionColor": [1.0, 1.0, 1.0],
                "sliceProjectionOpacity": 0.6,
                "lineThickness": 0.2,
                "lineColorFadingStart": 1.0,
                "lineColorFadingEnd": 10.0,
                "lineColorFadingSaturation": 1.0,
                "lineColorFadingHueOffset": 0.0,
                "handlesInteractive": false,
                "translationHandleVisibility": true,
                "rotationHandleVisibility": true,
                "scaleHandleVisibility": true,
                "interactionHandleScale": 3.0,
                "snapMode": "toVisibleSurface"
            }
        }
    ]
}